isagog/__init__.py
isagog/client/__init__.py
isagog/client/kg_client.py
isagog/client/nlp_client.py
isagog/generator/__init__.py
isagog/generator/sparql_generator.py
isagog/model/__init__.py
isagog/model/kg_model.py
isagog/model/kg_query.py
isagog/model/nlp_model.py
isagog/model/ontology.py
isagog_ai-1.0.1.dist-info/LICENSE
isagog_ai-1.0.1.dist-info/METADATA
isagog_ai-1.0.1.dist-info/WHEEL
isagog_ai-1.0.1.dist-info/RECORD
