Metadata-Version: 2.1
Name: isagog-ai
Version: 1.0.1
Summary: client for isagog ai services
Author: Guido Vetere
Author-email: g.vetere@isagog.com
Requires-Python: >=3.10,<4.0
Classifier: Programming Language :: Python :: 3
Classifier: Programming Language :: Python :: 3.10
Classifier: Programming Language :: Python :: 3.11
Classifier: Programming Language :: Python :: 3.12
Requires-Dist: httpx (>=0.27.0,<0.28.0)
Requires-Dist: pydantic (>=2.7.4,<3.0.0)
Requires-Dist: pytest (>=8.2.1,<9.0.0)
Requires-Dist: python-dotenv (>=1.0.0,<2.0.0)
Requires-Dist: rdflib (>=7.0.0,<8.0.0)
Requires-Dist: requests (>=2.32.1,<3.0.0)
Requires-Dist: toml (>=0.10.2,<0.11.0)
Requires-Dist: urllib3 (>=2.0.6,<3.0.0)
